plotapi/__init__.py
plotapi-8.0.0.dist-info/LICENSE
plotapi-8.0.0.dist-info/METADATA
plotapi-8.0.0.dist-info/WHEEL
plotapi-8.0.0.dist-info/top_level.txt
plotapi-8.0.0.dist-info/RECORD
