Metadata-Version: 2.1
Name: plotapi
Version: 8.0.0
Summary: Engaging visualisations, made easy.
Home-page: https://plotapi.com
Author: Dr. Shahin Rostami
Author-email: hello@shahinrostami.com
License: MIT
License-File: LICENSE
Requires-Dist: requests <3.0.0,>=2.20.0
